<?xml version="1.0" encoding="utf-8"?>
<tv generator-info-name="lps_crawler" source-info-name="angiangtv.vn"><channel id="atv3kg2"><display-name>An Giang 3</display-name></channel><programme start="20251112051500 +0700" stop="20251112052000 +0700" channel="atv3kg2"><title lang="vi">Nhạc hiệu – Chào cờ buổi sáng – Giới thiệu chương trình</title></programme><programme start="20251112052000 +0700" stop="20251112053000 +0700" channel="atv3kg2"><title lang="vi">Chương trình Hạt cát diệu kỳ - Số 23 - 04</title></programme><programme start="20251112053000 +0700" stop="20251112063000 +0700" channel="atv3kg2"><title lang="vi">Chương trình tiếng Khmer</title></programme><programme start="20251112063000 +0700" stop="20251112065000 +0700" channel="atv3kg2"><title lang="vi">Thời sự An Giang – Chương trình An Giang ngày mới</title></programme><programme start="20251112065000 +0700" stop="20251112070000 +0700" channel="atv3kg2"><title lang="vi">Ký sự: Hành trình theo chân Bác (tập 30)</title></programme><programme start="20251112070000 +0700" stop="20251112070500 +0700" channel="atv3kg2"><title lang="vi">Thông báo – nhắn tin</title></programme><programme start="20251112070500 +0700" stop="20251112073000 +0700" channel="atv3kg2"><title lang="vi">Ca nhạc: Dạ khúc Bolero – Số 24</title></programme><programme start="20251112073000 +0700" stop="20251112074500 +0700" channel="atv3kg2"><title lang="vi">Chuyên mục: Đối ngoại Nhân dân</title></programme><programme start="20251112074500 +0700" stop="20251112081000 +0700" channel="atv3kg2"><title lang="vi">Chương trình giải trí: Quán ăn hạnh phúc – Tập 9</title></programme><programme start="20251112081000 +0700" stop="20251112081500 +0700" channel="atv3kg2"><title lang="vi">Thông báo – Nhắn tin – Giới thiệu chương trình</title></programme><programme start="20251112081500 +0700" stop="20251112094500 +0700" channel="atv3kg2"><title lang="vi">Phim truyện nước ngoài: Người điều tra thương nghiệp – Tập 35 – 36</title></programme><programme start="20251112094500 +0700" stop="20251112104500 +0700" channel="atv3kg2"><title lang="vi">Chương trình tiếng Khmer</title></programme><programme start="20251112104500 +0700" stop="20251112110000 +0700" channel="atv3kg2"><title lang="vi">Chuyên mục: Bạn tri kỷ nhà nông</title></programme><programme start="20251112110000 +0700" stop="20251112113000 +0700" channel="atv3kg2"><title lang="vi">Phim Hoạt hình: Đội cứu hộ thành phố - Tập 88 - 89</title></programme><programme start="20251112113000 +0700" stop="20251112120000 +0700" channel="atv3kg2"><title lang="vi">Thời sự An Giang – Bản tin Quốc tế - Thể thao</title></programme><programme start="20251112120000 +0700" stop="20251112120500 +0700" channel="atv3kg2"><title lang="vi">Thông báo – Quảng cáo - Nhắn tin</title></programme><programme start="20251112120500 +0700" stop="20251112134500 +0700" channel="atv3kg2"><title lang="vi">Phim truyện nước ngoài: Cầu vồng trở lại – Tập 13 - 14</title></programme><programme start="20251112134500 +0700" stop="20251112141500 +0700" channel="atv3kg2"><title lang="vi">PTL: Việt Nam – thời đại HCM biên niên sử truyền hình (tập 23)</title></programme><programme start="20251112141500 +0700" stop="20251112151500 +0700" channel="atv3kg2"><title lang="vi">Phim truyện Việt Nam: Cần một bờ vai  – Tập 17</title></programme><programme start="20251112151500 +0700" stop="20251112161500 +0700" channel="atv3kg2"><title lang="vi">Chương trình tiếng Khmer</title></programme><programme start="20251112161500 +0700" stop="20251112180000 +0700" channel="atv3kg2"><title lang="vi">Phim truyện nước ngoài: Những nàng dâu bá đạo – Tập 20 - 21</title></programme><programme start="20251112180000 +0700" stop="20251112181500 +0700" channel="atv3kg2"><title lang="vi">Bản tin 18h</title></programme><programme start="20251112181500 +0700" stop="20251112183000 +0700" channel="atv3kg2"><title lang="vi">Bản tin Quốc tế - Thể thao</title></programme><programme start="20251112183000 +0700" stop="20251112184500 +0700" channel="atv3kg2"><title lang="vi">Chuyên mục: Làng nghề Việt (số 9)</title></programme><programme start="20251112184500 +0700" stop="20251112185500 +0700" channel="atv3kg2"><title lang="vi">Ký ức miền quê: Sắc màu Tà Pạ</title></programme><programme start="20251112185500 +0700" stop="20251112190000 +0700" channel="atv3kg2"><title lang="vi">Thông báo – Nhắn tin – Giới thiệu phim – Giới thiệu chương trình</title></programme><programme start="20251112190000 +0700" stop="20251112194500 +0700" channel="atv3kg2"><title lang="vi">Tiếp chuyển Thời sự Đài Truyền hình Việt Nam</title></programme><programme start="20251112194500 +0700" stop="20251112203000 +0700" channel="atv3kg2"><title lang="vi">Phim truyện Việt Nam: Ruby máu – Tập 11</title></programme><programme start="20251112203000 +0700" stop="20251112204500 +0700" channel="atv3kg2"><title lang="vi">Thông báo - Quảng cáo - Dự báo thời tiết</title></programme><programme start="20251112204500 +0700" stop="20251112210000 +0700" channel="atv3kg2"><title lang="vi">QHĐNCN: Rạch Giá Đất và Người</title></programme><programme start="20251112210000 +0700" stop="20251112213000 +0700" channel="atv3kg2"><title lang="vi">Thời sự An Giang</title></programme><programme start="20251112213000 +0700" stop="20251112221500 +0700" channel="atv3kg2"><title lang="vi">Phim truyện Trung Quốc: Hoắc Nguyên Giáp – Tập 14</title></programme><programme start="20251112221500 +0700" stop="20251112224500 +0700" channel="atv3kg2"><title lang="vi">Chương trình giải trí: Câu chuyện cảnh giác – Tập 9</title></programme><programme start="20251112224500 +0700" stop="20251112231500 +0700" channel="atv3kg2"><title lang="vi">Phim Sitcom: Cà phê tử tế - Tập 59</title></programme><programme start="20251112231500 +0700" stop="20251112232000 +0700" channel="atv3kg2"><title lang="vi">Dự báo thời tiết</title></programme><programme start="20251112232000 +0700" stop="20251112234500 +0700" channel="atv3kg2"><title lang="vi">Bản tin cuối ngày – Thế giới 24 giờ</title></programme><programme start="20251112234500 +0700" stop="20251113000000 +0700" channel="atv3kg2"><title lang="vi">Giới thiệu chương trình</title></programme></tv>