<?xml version="1.0" encoding="utf-8"?>
<tv generator-info-name="lps_crawler" source-info-name="angiangtv.vn"><channel id="atv3kg2"><display-name>An Giang 3</display-name></channel><programme start="20260318051500 +0700" stop="20260318051500 +0700" channel="atv3kg2"><title lang="vi">Nhạc hiệu – Chào cờ buổi sáng – Giới thiệu chương trình</title></programme><programme start="20260318051500 +0700" stop="20260318051500 +0700" channel="atv3kg2"><title lang="vi">Nhạc hiệu – Chào cờ buổi sáng – Giới thiệu chương trình</title></programme><programme start="20260318051500 +0700" stop="20260318051500 +0700" channel="atv3kg2"><title lang="vi">Nhạc hiệu – Chào cờ buổi sáng – Giới thiệu chương trình</title></programme><programme start="20260318051500 +0700" stop="20260318052000 +0700" channel="atv3kg2"><title lang="vi">Nhạc hiệu – Chào cờ buổi sáng – Giới thiệu chương trình</title></programme><programme start="20260318052000 +0700" stop="20260318052000 +0700" channel="atv3kg2"><title lang="vi">Chương trình giải trí: Mình ơi ăn gì – Tập 5 - 6</title></programme><programme start="20260318052000 +0700" stop="20260318052000 +0700" channel="atv3kg2"><title lang="vi">Chương trình giải trí: Mình ơi ăn gì – Tập 7 - 8</title></programme><programme start="20260318052000 +0700" stop="20260318052000 +0700" channel="atv3kg2"><title lang="vi">Chương trình giải trí: Mình ơi ăn gì – Tập 9 - 10</title></programme><programme start="20260318052000 +0700" stop="20260318053000 +0700" channel="atv3kg2"><title lang="vi">Chương trình giải trí: Mình ơi ăn gì – Tập 11 - 12</title></programme><programme start="20260318053000 +0700" stop="20260318053000 +0700" channel="atv3kg2"><title lang="vi">Chương trình tiếng Khmer</title></programme><programme start="20260318053000 +0700" stop="20260318053000 +0700" channel="atv3kg2"><title lang="vi">Chương trình tiếng Khmer</title></programme><programme start="20260318053000 +0700" stop="20260318063000 +0700" channel="atv3kg2"><title lang="vi">Chương trình tiếng Khmer</title></programme><programme start="20260318063000 +0700" stop="20260318063000 +0700" channel="atv3kg2"><title lang="vi">Thời sự An Giang – Chương trình An Giang ngày mới</title></programme><programme start="20260318063000 +0700" stop="20260318063000 +0700" channel="atv3kg2"><title lang="vi">Thời sự An Giang – Chương trình An Giang ngày mới</title></programme><programme start="20260318063000 +0700" stop="20260318063000 +0700" channel="atv3kg2"><title lang="vi">Thời sự An Giang – Chương trình An Giang ngày mới</title></programme><programme start="20260318063000 +0700" stop="20260318065000 +0700" channel="atv3kg2"><title lang="vi">Thời sự An Giang – Chương trình An Giang ngày mới</title></programme><programme start="20260318065000 +0700" stop="20260318065000 +0700" channel="atv3kg2"><title lang="vi">Ký ức miền quê: Đậm đà bún mắm Cà Chơi</title></programme><programme start="20260318065000 +0700" stop="20260318065000 +0700" channel="atv3kg2"><title lang="vi">Chuyên mục: Muôn màu cuộc sống (số 4)</title></programme><programme start="20260318065000 +0700" stop="20260318065000 +0700" channel="atv3kg2"><title lang="vi">Chuyên mục: Làng nghề Việt (số 5)</title></programme><programme start="20260318065000 +0700" stop="20260318070000 +0700" channel="atv3kg2"><title lang="vi">Chuyên mục: Vì an ninh Tổ quốc</title></programme><programme start="20260318070000 +0700" stop="20260318070000 +0700" channel="atv3kg2"><title lang="vi">Thông báo – nhắn tin</title></programme><programme start="20260318070000 +0700" stop="20260318070000 +0700" channel="atv3kg2"><title lang="vi">Thông báo – nhắn tin</title></programme><programme start="20260318070000 +0700" stop="20260318070000 +0700" channel="atv3kg2"><title lang="vi">Thông báo – nhắn tin</title></programme><programme start="20260318070000 +0700" stop="20260318070500 +0700" channel="atv3kg2"><title lang="vi">Thông báo – nhắn tin</title></programme><programme start="20260318070500 +0700" stop="20260318070500 +0700" channel="atv3kg2"><title lang="vi">Ca nhạc:  Chào An Giang 03</title></programme><programme start="20260318070500 +0700" stop="20260318070500 +0700" channel="atv3kg2"><title lang="vi">Ca nhạc: Tuyển tập nhạc trẻ 04</title></programme><programme start="20260318070500 +0700" stop="20260318070500 +0700" channel="atv3kg2"><title lang="vi">Ca nhạc:  Còn mãi những bài ca 1</title></programme><programme start="20260318070500 +0700" stop="20260318073000 +0700" channel="atv3kg2"><title lang="vi">Ca nhạc: Dạ khúc Bolero 2026 – Số 1</title></programme><programme start="20260318073000 +0700" stop="20260318073000 +0700" channel="atv3kg2"><title lang="vi">Chuyên mục: Giồng Riềng ngày mới</title></programme><programme start="20260318073000 +0700" stop="20260318073000 +0700" channel="atv3kg2"><title lang="vi">Chuyên mục: Chuyên mục: Làng nghề Việt (số 3)</title></programme><programme start="20260318073000 +0700" stop="20260318073000 +0700" channel="atv3kg2"><title lang="vi">Chuyên đề: Đảng trong cuộc sống hôm nay</title></programme><programme start="20260318073000 +0700" stop="20260318074500 +0700" channel="atv3kg2"><title lang="vi">Tạp chí: Nông nghiệp – Nông thôn</title></programme><programme start="20260318074500 +0700" stop="20260318074500 +0700" channel="atv3kg2"><title lang="vi">Chương trình giải trí: Quán ăn hạnh phúc – Tập 27</title></programme><programme start="20260318074500 +0700" stop="20260318074500 +0700" channel="atv3kg2"><title lang="vi">Thông báo – Nhắn tin – Giới thiệu chương trình</title></programme><programme start="20260318074500 +0700" stop="20260318074500 +0700" channel="atv3kg2"><title lang="vi">Chương trình giải trí: Bí ẩn Eva – Tập 31</title></programme><programme start="20260318074500 +0700" stop="20260318074500 +0700" channel="atv3kg2"><title lang="vi">Chương trình giải trí: 24 giờ nói thật – Tập 6</title></programme><programme start="20260318074500 +0700" stop="20260318081000 +0700" channel="atv3kg2"><title lang="vi">Chương trình giải trí: Hỏi bác sỹ chuyên khoa – Tập 7</title></programme><programme start="20260318081000 +0700" stop="20260318081000 +0700" channel="atv3kg2"><title lang="vi">Thông báo – Nhắn tin – Giới thiệu chương trình</title></programme><programme start="20260318081000 +0700" stop="20260318081000 +0700" channel="atv3kg2"><title lang="vi">Thông báo – Nhắn tin – Giới thiệu chương trình</title></programme><programme start="20260318081000 +0700" stop="20260318081000 +0700" channel="atv3kg2"><title lang="vi">Thông báo – Nhắn tin – Giới thiệu chương trình</title></programme><programme start="20260318081000 +0700" stop="20260318081500 +0700" channel="atv3kg2"><title lang="vi">Thông báo – Nhắn tin – Giới thiệu chương trình</title></programme><programme start="20260318081500 +0700" stop="20260318081500 +0700" channel="atv3kg2"><title lang="vi">Phim truyện nước ngoài: Người giàu cũng khóc – Tập 23 - 24</title></programme><programme start="20260318081500 +0700" stop="20260318081500 +0700" channel="atv3kg2"><title lang="vi">Phim truyện nước ngoài: Người giàu cũng khóc – Tập 25 - 26</title></programme><programme start="20260318081500 +0700" stop="20260318081500 +0700" channel="atv3kg2"><title lang="vi">Phim truyện nước ngoài: Người giàu cũng khóc – Tập 27 - 28</title></programme><programme start="20260318081500 +0700" stop="20260318094500 +0700" channel="atv3kg2"><title lang="vi">Phim truyện nước ngoài: Người giàu cũng khóc – Tập 29 - 30</title></programme><programme start="20260318094500 +0700" stop="20260318094500 +0700" channel="atv3kg2"><title lang="vi">Chương trình tiếng Khmer</title></programme><programme start="20260318094500 +0700" stop="20260318094500 +0700" channel="atv3kg2"><title lang="vi">Chương trình tiếng Khmer</title></programme><programme start="20260318094500 +0700" stop="20260318094500 +0700" channel="atv3kg2"><title lang="vi">Chương trình tiếng Khmer</title></programme><programme start="20260318094500 +0700" stop="20260318104500 +0700" channel="atv3kg2"><title lang="vi">Chương trình tiếng Khmer</title></programme><programme start="20260318104500 +0700" stop="20260318104500 +0700" channel="atv3kg2"><title lang="vi">Chương trình: Sách hay thay đổi cuộc đời (tập 3)</title></programme><programme start="20260318104500 +0700" stop="20260318104500 +0700" channel="atv3kg2"><title lang="vi">Chương trình: Sách hay thay đổi cuộc đời (tập 4)</title></programme><programme start="20260318104500 +0700" stop="20260318104500 +0700" channel="atv3kg2"><title lang="vi">Chương trình: Sách hay thay đổi cuộc đời (tập 5)</title></programme><programme start="20260318104500 +0700" stop="20260318110000 +0700" channel="atv3kg2"><title lang="vi">Chương trình: Sách hay thay đổi cuộc đời (tập 6)</title></programme><programme start="20260318110000 +0700" stop="20260318110000 +0700" channel="atv3kg2"><title lang="vi">Phim Hoạt hình: Đội cứu hộ thành phố - Tập 15 - 16</title></programme><programme start="20260318110000 +0700" stop="20260318110000 +0700" channel="atv3kg2"><title lang="vi">Phim Hoạt hình: Đội cứu hộ thành phố - Tập 17 - 18</title></programme><programme start="20260318110000 +0700" stop="20260318110000 +0700" channel="atv3kg2"><title lang="vi">Phim Hoạt hình: Đội cứu hộ thành phố - Tập 19 - 20</title></programme><programme start="20260318110000 +0700" stop="20260318113000 +0700" channel="atv3kg2"><title lang="vi">Phim Hoạt hình: Đội cứu hộ thành phố - Tập 21 - 22</title></programme><programme start="20260318113000 +0700" stop="20260318113000 +0700" channel="atv3kg2"><title lang="vi">Thời sự An Giang - Bản tin Quốc tế - Thể thao</title></programme><programme start="20260318113000 +0700" stop="20260318113000 +0700" channel="atv3kg2"><title lang="vi">Thời sự An Giang - Bản tin Quốc tế - Thể thao</title></programme><programme start="20260318113000 +0700" stop="20260318113000 +0700" channel="atv3kg2"><title lang="vi">Thời sự An Giang - Bản tin Quốc tế - Thể thao</title></programme><programme start="20260318113000 +0700" stop="20260318120000 +0700" channel="atv3kg2"><title lang="vi">Thời sự An Giang - Bản tin Quốc tế - Thể thao</title></programme><programme start="20260318120000 +0700" stop="20260318120000 +0700" channel="atv3kg2"><title lang="vi">Thông báo – Quảng cáo - Nhắn tin</title></programme><programme start="20260318120000 +0700" stop="20260318120000 +0700" channel="atv3kg2"><title lang="vi">Thông báo – Quảng cáo - Nhắn tin</title></programme><programme start="20260318120000 +0700" stop="20260318120000 +0700" channel="atv3kg2"><title lang="vi">Thông báo – Quảng cáo</title></programme><programme start="20260318120000 +0700" stop="20260318120500 +0700" channel="atv3kg2"><title lang="vi">Thông báo – Quảng cáo</title></programme><programme start="20260318120500 +0700" stop="20260318120500 +0700" channel="atv3kg2"><title lang="vi">Phim truyện nước ngoài: Lời hứa của tình yêu – Tập 27 - 28</title></programme><programme start="20260318120500 +0700" stop="20260318120500 +0700" channel="atv3kg2"><title lang="vi">Phim truyện nước ngoài: Lời hứa của tình yêu – Tập 29 - 30</title></programme><programme start="20260318120500 +0700" stop="20260318120500 +0700" channel="atv3kg2"><title lang="vi">Phim truyện nước ngoài: Lời hứa của tình yêu – Tập 31 – 32 – Hết</title></programme><programme start="20260318120500 +0700" stop="20260318134500 +0700" channel="atv3kg2"><title lang="vi">Phim truyện nước ngoài: Nam Bắc Đại Trạng Sư – Tập 1 - 2</title></programme><programme start="20260318134500 +0700" stop="20260318134500 +0700" channel="atv3kg2"><title lang="vi">PTL: Việt Nam - Thời đại Hồ Chí Minh biên niên sử truyền hình (tập 30)</title></programme><programme start="20260318134500 +0700" stop="20260318134500 +0700" channel="atv3kg2"><title lang="vi">PTL: Việt Nam - Thời đại Hồ Chí Minh biên niên sử truyền hình (tập 31)</title></programme><programme start="20260318134500 +0700" stop="20260318134500 +0700" channel="atv3kg2"><title lang="vi">PTL: Việt Nam - Thời đại Hồ Chí Minh biên niên sử truyền hình (tập 32)</title></programme><programme start="20260318134500 +0700" stop="20260318141500 +0700" channel="atv3kg2"><title lang="vi">PTL: Việt Nam - Thời đại Hồ Chí Minh biên niên sử truyền hình (tập 33)</title></programme><programme start="20260318141500 +0700" stop="20260318141500 +0700" channel="atv3kg2"><title lang="vi">Phim truyện Việt Nam: Lao công bí ẩn – Tập 16</title></programme><programme start="20260318141500 +0700" stop="20260318141500 +0700" channel="atv3kg2"><title lang="vi">Phim truyện Việt Nam: Lao công bí ẩn – Tập 17</title></programme><programme start="20260318141500 +0700" stop="20260318141500 +0700" channel="atv3kg2"><title lang="vi">Phim truyện Việt Nam: Lao công bí ẩn – Tập 18</title></programme><programme start="20260318141500 +0700" stop="20260318151500 +0700" channel="atv3kg2"><title lang="vi">Phim truyện Việt Nam: Lao công bí ẩn – Tập 19</title></programme><programme start="20260318151500 +0700" stop="20260318151500 +0700" channel="atv3kg2"><title lang="vi">Chương trình tiếng Khmer</title></programme><programme start="20260318151500 +0700" stop="20260318151500 +0700" channel="atv3kg2"><title lang="vi">Chương trình tiếng Khmer</title></programme><programme start="20260318151500 +0700" stop="20260318151500 +0700" channel="atv3kg2"><title lang="vi">Chương trình tiếng Khmer</title></programme><programme start="20260318151500 +0700" stop="20260318161500 +0700" channel="atv3kg2"><title lang="vi">Chương trình tiếng Khmer</title></programme><programme start="20260318161500 +0700" stop="20260318161500 +0700" channel="atv3kg2"><title lang="vi">Phim truyện nước ngoài: Sợi dây chuyền định mệnh – Tập 9 - 10</title></programme><programme start="20260318161500 +0700" stop="20260318161500 +0700" channel="atv3kg2"><title lang="vi">Phim truyện nước ngoài: Sợi dây chuyền định mệnh – Tập 11 - 12</title></programme><programme start="20260318161500 +0700" stop="20260318161500 +0700" channel="atv3kg2"><title lang="vi">Phim truyện nước ngoài: Sợi dây chuyền định mệnh – Tập 13 - 14</title></programme><programme start="20260318161500 +0700" stop="20260318180000 +0700" channel="atv3kg2"><title lang="vi">Phim truyện nước ngoài:  Sợi dây chuyền định mệnh – Tập 15 - 16</title></programme><programme start="20260318180000 +0700" stop="20260318180000 +0700" channel="atv3kg2"><title lang="vi">Bản tin 18h</title></programme><programme start="20260318180000 +0700" stop="20260318180000 +0700" channel="atv3kg2"><title lang="vi">Bản tin 18h</title></programme><programme start="20260318180000 +0700" stop="20260318180000 +0700" channel="atv3kg2"><title lang="vi">Bản tin 18h</title></programme><programme start="20260318180000 +0700" stop="20260318181500 +0700" channel="atv3kg2"><title lang="vi">Bản tin 18h</title></programme><programme start="20260318181500 +0700" stop="20260318181500 +0700" channel="atv3kg2"><title lang="vi">Bản tin Quốc tế - Thể thao</title></programme><programme start="20260318181500 +0700" stop="20260318181500 +0700" channel="atv3kg2"><title lang="vi">Bản tin Quốc tế - Thể thao</title></programme><programme start="20260318181500 +0700" stop="20260318181500 +0700" channel="atv3kg2"><title lang="vi">Bản tin Quốc tế - Thể thao</title></programme><programme start="20260318181500 +0700" stop="20260318183000 +0700" channel="atv3kg2"><title lang="vi">Bản tin Quốc tế - Thể thao</title></programme><programme start="20260318183000 +0700" stop="20260318183000 +0700" channel="atv3kg2"><title lang="vi">Ca nhạc: Tuyển tập Bolero 18</title></programme><programme start="20260318183000 +0700" stop="20260318183000 +0700" channel="atv3kg2"><title lang="vi">Ca cổ: Dòng sông thời gian 2</title></programme><programme start="20260318183000 +0700" stop="20260318183000 +0700" channel="atv3kg2"><title lang="vi">Ca cổ:  Mật ngọt hương đời 2</title></programme><programme start="20260318183000 +0700" stop="20260318185500 +0700" channel="atv3kg2"><title lang="vi">Ca cổ: Âm thanh phù sa – Tập 4</title></programme><programme start="20260318185500 +0700" stop="20260318185500 +0700" channel="atv3kg2"><title lang="vi">Thông báo – Nhắn tin – Giới thiệu phim – Giới thiệu chương trình</title></programme><programme start="20260318185500 +0700" stop="20260318185500 +0700" channel="atv3kg2"><title lang="vi">Thông báo – Nhắn tin – Giới thiệu phim – Giới thiệu chương trình</title></programme><programme start="20260318185500 +0700" stop="20260318185500 +0700" channel="atv3kg2"><title lang="vi">Thông báo – Nhắn tin – Giới thiệu phim – Giới thiệu chương trình</title></programme><programme start="20260318185500 +0700" stop="20260318190000 +0700" channel="atv3kg2"><title lang="vi">Thông báo – Nhắn tin – Giới thiệu phim – Giới thiệu chương trình</title></programme><programme start="20260318190000 +0700" stop="20260318190000 +0700" channel="atv3kg2"><title lang="vi">Tiếp chuyển Thời sự Đài Truyền hình Việt Nam</title></programme><programme start="20260318190000 +0700" stop="20260318190000 +0700" channel="atv3kg2"><title lang="vi">Tiếp chuyển Thời sự Đài Truyền hình Việt Nam</title></programme><programme start="20260318190000 +0700" stop="20260318190000 +0700" channel="atv3kg2"><title lang="vi">Tiếp chuyển Thời sự Đài Truyền hình Việt Nam</title></programme><programme start="20260318190000 +0700" stop="20260318194500 +0700" channel="atv3kg2"><title lang="vi">Tiếp chuyển Thời sự Đài Truyền hình Việt Nam</title></programme><programme start="20260318194500 +0700" stop="20260318194500 +0700" channel="atv3kg2"><title lang="vi">Phim truyện Việt Nam: Những phận đời trớ trêu – Tập 14</title></programme><programme start="20260318194500 +0700" stop="20260318194500 +0700" channel="atv3kg2"><title lang="vi">Phim truyện Việt Nam: Những phận đời trớ trêu – Tập 15</title></programme><programme start="20260318194500 +0700" stop="20260318194500 +0700" channel="atv3kg2"><title lang="vi">Phim truyện Việt Nam: Những phận đời trớ trêu – Tập 16</title></programme><programme start="20260318194500 +0700" stop="20260318203000 +0700" channel="atv3kg2"><title lang="vi">Phim truyện Việt Nam: Những phận đời trớ trêu – Tập 17</title></programme><programme start="20260318203000 +0700" stop="20260318203000 +0700" channel="atv3kg2"><title lang="vi">Thông báo - Quảng cáo - Dự báo thời tiết</title></programme><programme start="20260318203000 +0700" stop="20260318203000 +0700" channel="atv3kg2"><title lang="vi">Thông báo – Quảng cáo – Dự báo thời tiết</title></programme><programme start="20260318203000 +0700" stop="20260318203000 +0700" channel="atv3kg2"><title lang="vi">Thông báo – Quảng cáo</title></programme><programme start="20260318203000 +0700" stop="20260318204500 +0700" channel="atv3kg2"><title lang="vi">Thông báo – Quảng cáo – Dự báo thời tiết</title></programme><programme start="20260318204500 +0700" stop="20260318204500 +0700" channel="atv3kg2"><title lang="vi">Ký ức miền quê: Bánh lá dừa món quà quê đi cùng năm tháng</title></programme><programme start="20260318204500 +0700" stop="20260318204500 +0700" channel="atv3kg2"><title lang="vi">Ký ức miền quê: Chuyện bắt cá đồng mùa nước lên</title></programme><programme start="20260318204500 +0700" stop="20260318204500 +0700" channel="atv3kg2"><title lang="vi">Chương trình: Khát vọng sống</title></programme><programme start="20260318204500 +0700" stop="20260318210000 +0700" channel="atv3kg2"><title lang="vi">Quê hương – Đất nước – Con người:  Sinh kế bền vững ở vùng đệm U Minh Thượng</title></programme><programme start="20260318210000 +0700" stop="20260318210000 +0700" channel="atv3kg2"><title lang="vi">Thời sự An Giang</title></programme><programme start="20260318210000 +0700" stop="20260318210000 +0700" channel="atv3kg2"><title lang="vi">Thời sự An Giang</title></programme><programme start="20260318210000 +0700" stop="20260318210000 +0700" channel="atv3kg2"><title lang="vi">Thời sự An Giang</title></programme><programme start="20260318210000 +0700" stop="20260318213000 +0700" channel="atv3kg2"><title lang="vi">Thời sự An Giang</title></programme><programme start="20260318213000 +0700" stop="20260318213000 +0700" channel="atv3kg2"><title lang="vi">Phim truyện Trung Quốc: Nhân tình của tổng tài – Tâp 19</title></programme><programme start="20260318213000 +0700" stop="20260318213000 +0700" channel="atv3kg2"><title lang="vi">Phim truyện Trung Quốc: Nhân tình của tổng tài – Tâp 20</title></programme><programme start="20260318213000 +0700" stop="20260318213000 +0700" channel="atv3kg2"><title lang="vi">Phim truyện Trung Quốc: Nhân tình của tổng tài – Tâp 21</title></programme><programme start="20260318213000 +0700" stop="20260318221500 +0700" channel="atv3kg2"><title lang="vi">Phim truyện Việt Nam: Nhân tình của tổng tài – Tâp 22</title></programme><programme start="20260318221500 +0700" stop="20260318221500 +0700" channel="atv3kg2"><title lang="vi">Chương trình giải trí: Hỏi bác sỹ chuyên khoa – Tập 8</title></programme><programme start="20260318221500 +0700" stop="20260318221500 +0700" channel="atv3kg2"><title lang="vi">Chương trình giải trí: Bách nghệ kỳ thú - Tập 7</title></programme><programme start="20260318221500 +0700" stop="20260318221500 +0700" channel="atv3kg2"><title lang="vi">Chương trình giải trí: Hẹn Hò với ngôi sao 2025 – Tập 2</title></programme><programme start="20260318221500 +0700" stop="20260318223000 +0700" channel="atv3kg2"><title lang="vi">Chương trình giải trí: 24h nói thật – Tập 3</title></programme><programme start="20260318223000 +0700" stop="20260318224500 +0700" channel="atv3kg2"><title lang="vi">Phim Sitcom: Cà phê tử tế - Tập 169</title></programme><programme start="20260318224500 +0700" stop="20260318224500 +0700" channel="atv3kg2"><title lang="vi">Phim Sitcom: Cà phê tử tế - Tập 167</title></programme><programme start="20260318224500 +0700" stop="20260318224500 +0700" channel="atv3kg2"><title lang="vi">Phim Sitcom: Cà phê tử tế - Tập 168</title></programme><programme start="20260318224500 +0700" stop="20260318231500 +0700" channel="atv3kg2"><title lang="vi">Phim Sitcom: Cà phê tử tế - Tập 170</title></programme><programme start="20260318231500 +0700" stop="20260318231500 +0700" channel="atv3kg2"><title lang="vi">Dự báo thời tiết</title></programme><programme start="20260318231500 +0700" stop="20260318231500 +0700" channel="atv3kg2"><title lang="vi">Dự báo thời tiết</title></programme><programme start="20260318231500 +0700" stop="20260318231500 +0700" channel="atv3kg2"><title lang="vi">Dự báo thời tiết</title></programme><programme start="20260318231500 +0700" stop="20260318232000 +0700" channel="atv3kg2"><title lang="vi">Dự báo thời tiết</title></programme><programme start="20260318232000 +0700" stop="20260318232000 +0700" channel="atv3kg2"><title lang="vi">Bản tin cuối ngày + Thế giới 24h</title></programme><programme start="20260318232000 +0700" stop="20260318232000 +0700" channel="atv3kg2"><title lang="vi">Bản tin cuối ngày – Thế giới 24h</title></programme><programme start="20260318232000 +0700" stop="20260318232000 +0700" channel="atv3kg2"><title lang="vi">Bản tin cuối ngày – Thế giới 24h</title></programme><programme start="20260318232000 +0700" stop="20260318234500 +0700" channel="atv3kg2"><title lang="vi">Bản tin cuối ngày – Thế giới 24h</title></programme><programme start="20260318234500 +0700" stop="20260318234500 +0700" channel="atv3kg2"><title lang="vi">Giới thiệu chương trình</title></programme><programme start="20260318234500 +0700" stop="20260318234500 +0700" channel="atv3kg2"><title lang="vi">Giới thiệu chương trình</title></programme><programme start="20260318234500 +0700" stop="20260318234500 +0700" channel="atv3kg2"><title lang="vi">Giới thiệu chương trình</title></programme><programme start="20260318234500 +0700" stop="20260319000000 +0700" channel="atv3kg2"><title lang="vi">Giới thiệu chương trình</title></programme></tv>