<?xml version='1.0' encoding='utf-8'?>
<tv source-info-name="msky.vn" generator-info-name="lps_crawler">
  <channel id="boomerang">
    <display-name>CARTOONITO</display-name>
    <url>https://info.msky.vn/vn/Boomerang.html</url>
  </channel>
  <programme start="20260331000000 +0700" stop="20260331010000 +0700" channel="boomerang">
    <title lang="vi">ella giữa những vì sao xa</title>
    <title lang="en">interstellar ella</title>
  </programme>
  <programme start="20260331010000 +0700" stop="20260331020000 +0700" channel="boomerang">
    <title lang="vi">ella giữa những vì sao xa</title>
    <title lang="en">interstellar ella</title>
  </programme>
  <programme start="20260331020000 +0700" stop="20260331030000 +0700" channel="boomerang">
    <title lang="vi">chú nhện lucas</title>
    <title lang="en">lucas the spider</title>
  </programme>
  <programme start="20260331030000 +0700" stop="20260331040000 +0700" channel="boomerang">
    <title lang="vi">chú nhện lucas</title>
    <title lang="en">lucas the spider</title>
  </programme>
  <programme start="20260331040000 +0700" stop="20260331050000 +0700" channel="boomerang">
    <title lang="vi">trang trại khủng long</title>
    <title lang="en">dino ranch</title>
  </programme>
  <programme start="20260331050000 +0700" stop="20260331060000 +0700" channel="boomerang">
    <title lang="vi">trang trại khủng long</title>
    <title lang="en">dino ranch</title>
  </programme>
  <programme start="20260331060000 +0700" stop="20260331070000 +0700" channel="boomerang">
    <title lang="vi">những giai điệu ngốc nghếch thời thơ ấu</title>
    <title lang="en">baby looney tunes</title>
  </programme>
  <programme start="20260331070000 +0700" stop="20260331073000 +0700" channel="boomerang">
    <title lang="vi">ban nhạc rock nhí</title>
    <title lang="en">mini beat power rockers</title>
  </programme>
  <programme start="20260331073000 +0700" stop="20260331080000 +0700" channel="boomerang">
    <title lang="vi">alice và lewis</title>
    <title lang="en">alice</title>
  </programme>
  <programme start="20260331080000 +0700" stop="20260331083000 +0700" channel="boomerang">
    <title lang="vi">kiểm lâm rob</title>
    <title lang="en">ranger rob</title>
  </programme>
  <programme start="20260331083000 +0700" stop="20260331090000 +0700" channel="boomerang">
    <title lang="vi">gấu xám và những chú chuột lemmut</title>
    <title lang="en">grizzy and the lemmings</title>
  </programme>
  <programme start="20260331090000 +0700" stop="20260331093000 +0700" channel="boomerang">
    <title lang="vi">ban nhạc rock nhí</title>
    <title lang="en">mini beat power rockers</title>
  </programme>
  <programme start="20260331093000 +0700" stop="20260331100000 +0700" channel="boomerang">
    <title lang="vi">những giai điệu ngốc nghếch thời thơ ấu</title>
    <title lang="en">baby looney tunes</title>
  </programme>
  <programme start="20260331100000 +0700" stop="20260331103000 +0700" channel="boomerang">
    <title lang="vi">thế giới nhỏ bao la của jessica</title>
    <title lang="en">jessica's big little world</title>
  </programme>
  <programme start="20260331103000 +0700" stop="20260331110000 +0700" channel="boomerang">
    <title lang="vi">tom biết nói: tổ đội anh hùng</title>
    <title lang="en">talking tom heroes: suddenly super</title>
  </programme>
  <programme start="20260331110000 +0700" stop="20260331113000 +0700" channel="boomerang">
    <title lang="vi">chương trình tom và jerry</title>
    <title lang="en">the tom and jerry show</title>
  </programme>
  <programme start="20260331113000 +0700" stop="20260331120000 +0700" channel="boomerang">
    <title lang="vi">dorothy và phù thủy xứ oz</title>
    <title lang="en">dorothy and the wizard of oz</title>
  </programme>
  <programme start="20260331120000 +0700" stop="20260331123000 +0700" channel="boomerang">
    <title lang="vi">chú nhện lucas</title>
    <title lang="en">lucas the spider</title>
  </programme>
  <programme start="20260331123000 +0700" stop="20260331130000 +0700" channel="boomerang">
    <title lang="vi">ban nhạc rock nhí</title>
    <title lang="en">mini beat power rockers</title>
  </programme>
  <programme start="20260331130000 +0700" stop="20260331133000 +0700" channel="boomerang">
    <title lang="vi">những giai điệu ngốc nghếch thời thơ ấu</title>
    <title lang="en">baby looney tunes</title>
  </programme>
  <programme start="20260331133000 +0700" stop="20260331140000 +0700" channel="boomerang">
    <title lang="vi">đội thợ xây của thỏ bugs</title>
    <title lang="en">bugs bunny builders</title>
  </programme>
  <programme start="20260331140000 +0700" stop="20260331143000 +0700" channel="boomerang">
    <title lang="vi">biệt đội xe dơi</title>
    <title lang="en">batwheels</title>
  </programme>
  <programme start="20260331143000 +0700" stop="20260331150000 +0700" channel="boomerang">
    <title lang="vi">chương trình tom và jerry</title>
    <title lang="en">the tom and jerry show</title>
  </programme>
  <programme start="20260331150000 +0700" stop="20260331153000 +0700" channel="boomerang">
    <title lang="vi">chương trình tom và jerry</title>
    <title lang="en">the tom and jerry show</title>
  </programme>
  <programme start="20260331153000 +0700" stop="20260331160000 +0700" channel="boomerang">
    <title lang="vi">gấu xám và những chú chuột lemmut</title>
    <title lang="en">grizzy and the lemmings</title>
  </programme>
  <programme start="20260331160000 +0700" stop="20260331163000 +0700" channel="boomerang">
    <title lang="vi">gấu xám và những chú chuột lemmut</title>
    <title lang="en">grizzy and the lemmings</title>
  </programme>
  <programme start="20260331163000 +0700" stop="20260331170000 +0700" channel="boomerang">
    <title lang="vi">alice và lewis</title>
    <title lang="en">alice</title>
  </programme>
  <programme start="20260331170000 +0700" stop="20260331173000 +0700" channel="boomerang">
    <title lang="vi">thế giới của barney</title>
    <title lang="en">barney's world</title>
  </programme>
  <programme start="20260331173000 +0700" stop="20260331175500 +0700" channel="boomerang">
    <title lang="vi">đội thợ xây của thỏ bugs</title>
    <title lang="en">bugs bunny builders</title>
  </programme>
  <programme start="20260331175500 +0700" stop="20260331180000 +0700" channel="boomerang">
    <title lang="vi">đội thợ xây của thỏ bugs</title>
    <title lang="en">bugs bunny builders: hard hat time</title>
  </programme>
  <programme start="20260331180000 +0700" stop="20260331183000 +0700" channel="boomerang">
    <title lang="vi">thế giới nhỏ bao la của jessica</title>
    <title lang="en">jessica's big little world</title>
  </programme>
  <programme start="20260331183000 +0700" stop="20260331190000 +0700" channel="boomerang">
    <title lang="vi">biệt đội xe dơi</title>
    <title lang="en">batwheels</title>
  </programme>
  <programme start="20260331190000 +0700" stop="20260331193000 +0700" channel="boomerang">
    <title lang="vi">ban nhạc rock nhí</title>
    <title lang="en">mini beat power rockers</title>
  </programme>
  <programme start="20260331193000 +0700" stop="20260331200000 +0700" channel="boomerang">
    <title lang="vi">những giai điệu ngốc nghếch thời thơ ấu</title>
    <title lang="en">baby looney tunes</title>
  </programme>
  <programme start="20260331200000 +0700" stop="20260331203000 +0700" channel="boomerang">
    <title lang="vi">gấu xám và những chú chuột lemmut</title>
    <title lang="en">grizzy and the lemmings</title>
  </programme>
  <programme start="20260331203000 +0700" stop="20260331210000 +0700" channel="boomerang">
    <title lang="vi">gấu xám và những chú chuột lemmut</title>
    <title lang="en">grizzy and the lemmings</title>
  </programme>
  <programme start="20260331210000 +0700" stop="20260331213000 +0700" channel="boomerang">
    <title lang="vi">đội chế tạo mecha</title>
    <title lang="en">mecha builders</title>
  </programme>
  <programme start="20260331213000 +0700" stop="20260331220000 +0700" channel="boomerang">
    <title lang="vi">đội chế tạo mecha</title>
    <title lang="en">mecha builders</title>
  </programme>
  <programme start="20260331220000 +0700" stop="20260331230000 +0700" channel="boomerang">
    <title lang="vi">đội thợ xây của thỏ bugs</title>
    <title lang="en">bugs bunny builders</title>
  </programme>
  <programme start="20260331230000 +0700" stop="20260331233000 +0700" channel="boomerang">
    <title lang="vi">những giai điệu ngốc nghếch thời thơ ấu</title>
    <title lang="en">baby looney tunes</title>
  </programme>
</tv>